Metadata-Version: 2.1
Name: Sahej-lib
Version: 0.0.1
Summary: Small library for limited and basic functions
Home-page: UNKNOWN
Author: Sahej Soin
License: UNKNOWN
Platform: UNKNOWN
